{"cameraMode":{"drawMode":0,"name":"Shaded","section":"Shading Mode"},"sceneLighting":true,"audioPlay":false,"sceneViewState":{"m_AlwaysRefresh":false,"showFog":false,"showSkybox":true,"showFlares":true,"showImageEffects":true,"showParticleSystems":true,"showVisualEffectGraphs":true,"m_FxEnabled":true},"in2DMode":false,"pivot":{"x":34.14544677734375,"y":-7.160336494445801,"z":68.16152954101563},"rotation":{"x":-0.3301607668399811,"y":0.2172885537147522,"z":-0.0783834233880043,"w":-0.9152334928512573},"size":9.538383483886719,"orthographic":false}